{
  "routes": {
    "/": {},
    "/dashboard": {},
    "/dashboard/accesorios": {},
    "/dashboard/blog": {},
    "/dashboard/cart": {},
    "/dashboard/galery": {},
    "/dashboard/home": {},
    "/dashboard/luminarias de mesa": {},
    "/dashboard/luminarias de pared": {},
    "/dashboard/luminarias de pie": {},
    "/dashboard/luminarias de techo": {},
    "/dashboard/team": {},
    "/login": {},
    "/login/change-pass": {},
    "/login/forgot-password": {},
    "/login/signin": {},
    "/login/signup": {}
  }
}